[
    {
        "kungorelseid": "K148815/24",
        "uppgiftslamnare": "Bolagsverket",
        "kungorelsetyp": "Aktiebolagsregistret",
        "personOrgnummer": "",
        "namn": "Andeme AB",
        "publiceringsdatum": "2024-02-28"
    },
    {
        "kungorelseid": "K148958/24",
        "uppgiftslamnare": "Bolagsverket",
        "kungorelsetyp": "Aktiebolagsregistret",
        "personOrgnummer": "",
        "namn": "Bodzie AB",
        "publiceringsdatum": "2024-02-28"
    },
    {
        "kungorelseid": "K148964/24",
        "uppgiftslamnare": "Bolagsverket",
        "kungorelsetyp": "Aktiebolagsregistret",
        "personOrgnummer": "",
        "namn": "Taurus Rex AB",
        "publiceringsdatum": "2024-02-28"
    },
    {
        "kungorelseid": "K149326/24",
        "uppgiftslamnare": "Bolagsverket",
        "kungorelsetyp": "Aktiebolagsregistret",
        "personOrgnummer": "",
        "namn": "G\u00e4llivare Kyrkoherden 6 Fastigheter AB",
        "publiceringsdatum": "2024-02-28"
    },
    {
        "kungorelseid": "K149328/24",
        "uppgiftslamnare": "Bolagsverket",
        "kungorelsetyp": "Aktiebolagsregistret",
        "personOrgnummer": "",
        "namn": "Hummerhielm & Co AB",
        "publiceringsdatum": "2024-02-28"
    },
    {
        "kungorelseid": "K148848/24",
        "uppgiftslamnare": "Bolagsverket",
        "kungorelsetyp": "Aktiebolagsregistret",
        "personOrgnummer": "",
        "namn": "HER Law AB",
        "publiceringsdatum": "2024-02-28"
    },
    {
        "kungorelseid": "K148998/24",
        "uppgiftslamnare": "Bolagsverket",
        "kungorelsetyp": "Aktiebolagsregistret",
        "personOrgnummer": "",
        "namn": "Tors Consulting i L\u00f6ddek\u00f6pinge AB",
        "publiceringsdatum": "2024-02-28"
    },
    {
        "kungorelseid": "K148999/24",
        "uppgiftslamnare": "Bolagsverket",
        "kungorelsetyp": "Aktiebolagsregistret",
        "personOrgnummer": "",
        "namn": "PrintPeak Solutions AB",
        "publiceringsdatum": "2024-02-28"
    },
    {
        "kungorelseid": "K149394/24",
        "uppgiftslamnare": "Bolagsverket",
        "kungorelsetyp": "Aktiebolagsregistret",
        "personOrgnummer": "",
        "namn": "AD Konsult och R\u00e5dgivning AB",
        "publiceringsdatum": "2024-02-28"
    },
    {
        "kungorelseid": "K149397/24",
        "uppgiftslamnare": "Bolagsverket",
        "kungorelsetyp": "Aktiebolagsregistret",
        "personOrgnummer": "",
        "namn": "Plaka Malaka AB",
        "publiceringsdatum": "2024-02-28"
    },
    {
        "kungorelseid": "K149001/24",
        "uppgiftslamnare": "Bolagsverket",
        "kungorelsetyp": "Aktiebolagsregistret",
        "personOrgnummer": "",
        "namn": "Sk\u00e5\u00e5res VVS Service Grums AB",
        "publiceringsdatum": "2024-02-28"
    },
    {
        "kungorelseid": "K149405/24",
        "uppgiftslamnare": "Bolagsverket",
        "kungorelsetyp": "Aktiebolagsregistret",
        "personOrgnummer": "",
        "namn": "Jora Future AB",
        "publiceringsdatum": "2024-02-28"
    },
    {
        "kungorelseid": "K149406/24",
        "uppgiftslamnare": "Bolagsverket",
        "kungorelsetyp": "Aktiebolagsregistret",
        "personOrgnummer": "",
        "namn": "L\u00f6voll Filmkonsult AB",
        "publiceringsdatum": "2024-02-28"
    },
    {
        "kungorelseid": "K149407/24",
        "uppgiftslamnare": "Bolagsverket",
        "kungorelsetyp": "Aktiebolagsregistret",
        "personOrgnummer": "",
        "namn": "TUMIUM AB",
        "publiceringsdatum": "2024-02-28"
    },
    {
        "kungorelseid": "K149409/24",
        "uppgiftslamnare": "Bolagsverket",
        "kungorelsetyp": "Aktiebolagsregistret",
        "personOrgnummer": "",
        "namn": "Martin Wallgren Music Productions AB",
        "publiceringsdatum": "2024-02-28"
    },
    {
        "kungorelseid": "K149411/24",
        "uppgiftslamnare": "Bolagsverket",
        "kungorelsetyp": "Aktiebolagsregistret",
        "personOrgnummer": "",
        "namn": "Pendro & Co AB",
        "publiceringsdatum": "2024-02-28"
    },
    {
        "kungorelseid": "K149423/24",
        "uppgiftslamnare": "Bolagsverket",
        "kungorelsetyp": "Aktiebolagsregistret",
        "personOrgnummer": "",
        "namn": "Emil Olsson Tandv\u00e5rd AB",
        "publiceringsdatum": "2024-02-28"
    },
    {
        "kungorelseid": "K149431/24",
        "uppgiftslamnare": "Bolagsverket",
        "kungorelsetyp": "Aktiebolagsregistret",
        "personOrgnummer": "",
        "namn": "leg. psykolog Linda Karlsson AB",
        "publiceringsdatum": "2024-02-28"
    },
    {
        "kungorelseid": "K149432/24",
        "uppgiftslamnare": "Bolagsverket",
        "kungorelsetyp": "Aktiebolagsregistret",
        "personOrgnummer": "",
        "namn": "RR Tak i J\u00e4rf\u00e4lla AB",
        "publiceringsdatum": "2024-02-28"
    },
    {
        "kungorelseid": "K149437/24",
        "uppgiftslamnare": "Bolagsverket",
        "kungorelsetyp": "Aktiebolagsregistret",
        "personOrgnummer": "",
        "namn": "Anna Winck AB",
        "publiceringsdatum": "2024-02-28"
    },
    {
        "kungorelseid": "K149438/24",
        "uppgiftslamnare": "Bolagsverket",
        "kungorelsetyp": "Aktiebolagsregistret",
        "personOrgnummer": "",
        "namn": "Ninmar Holding AB",
        "publiceringsdatum": "2024-02-28"
    },
    {
        "kungorelseid": "K149358/24",
        "uppgiftslamnare": "Bolagsverket",
        "kungorelsetyp": "Aktiebolagsregistret",
        "personOrgnummer": "",
        "namn": "Avedisian systrarna AB",
        "publiceringsdatum": "2024-02-28"
    },
    {
        "kungorelseid": "K149360/24",
        "uppgiftslamnare": "Bolagsverket",
        "kungorelsetyp": "Aktiebolagsregistret",
        "personOrgnummer": "",
        "namn": "Advokat Marie Johnsson AB",
        "publiceringsdatum": "2024-02-28"
    },
    {
        "kungorelseid": "K149362/24",
        "uppgiftslamnare": "Bolagsverket",
        "kungorelsetyp": "Aktiebolagsregistret",
        "personOrgnummer": "",
        "namn": "Gamla Real Holding AB",
        "publiceringsdatum": "2024-02-28"
    },
    {
        "kungorelseid": "K149364/24",
        "uppgiftslamnare": "Bolagsverket",
        "kungorelsetyp": "Aktiebolagsregistret",
        "personOrgnummer": "",
        "namn": "SveaSoft AB",
        "publiceringsdatum": "2024-02-28"
    },
    {
        "kungorelseid": "K149373/24",
        "uppgiftslamnare": "Bolagsverket",
        "kungorelsetyp": "Aktiebolagsregistret",
        "personOrgnummer": "",
        "namn": "DP Sweden AB",
        "publiceringsdatum": "2024-02-28"
    },
    {
        "kungorelseid": "K149376/24",
        "uppgiftslamnare": "Bolagsverket",
        "kungorelsetyp": "Aktiebolagsregistret",
        "personOrgnummer": "",
        "namn": "Solliden Kompass AB",
        "publiceringsdatum": "2024-02-28"
    },
    {
        "kungorelseid": "K149382/24",
        "uppgiftslamnare": "Bolagsverket",
        "kungorelsetyp": "Aktiebolagsregistret",
        "personOrgnummer": "",
        "namn": "GMM Transport AB",
        "publiceringsdatum": "2024-02-28"
    },
    {
        "kungorelseid": "K149383/24",
        "uppgiftslamnare": "Bolagsverket",
        "kungorelsetyp": "Aktiebolagsregistret",
        "personOrgnummer": "",
        "namn": "Bauld Media AB",
        "publiceringsdatum": "2024-02-28"
    },
    {
        "kungorelseid": "K149127/24",
        "uppgiftslamnare": "Bolagsverket",
        "kungorelsetyp": "Aktiebolagsregistret",
        "personOrgnummer": "",
        "namn": "Jilk\u00e9n Nordic Food Tourism AB",
        "publiceringsdatum": "2024-02-28"
    },
    {
        "kungorelseid": "K149005/24",
        "uppgiftslamnare": "Bolagsverket",
        "kungorelsetyp": "Aktiebolagsregistret",
        "personOrgnummer": "",
        "namn": "Explicit AB",
        "publiceringsdatum": "2024-02-28"
    },
    {
        "kungorelseid": "K149055/24",
        "uppgiftslamnare": "Bolagsverket",
        "kungorelsetyp": "Aktiebolagsregistret",
        "personOrgnummer": "",
        "namn": "Marvidson Consultancy Group AB",
        "publiceringsdatum": "2024-02-28"
    },
    {
        "kungorelseid": "K149061/24",
        "uppgiftslamnare": "Bolagsverket",
        "kungorelsetyp": "Aktiebolagsregistret",
        "personOrgnummer": "",
        "namn": "Chanle Group AB",
        "publiceringsdatum": "2024-02-28"
    },
    {
        "kungorelseid": "K149109/24",
        "uppgiftslamnare": "Bolagsverket",
        "kungorelsetyp": "Aktiebolagsregistret",
        "personOrgnummer": "",
        "namn": "VVSFIX STOCKHOLM AB",
        "publiceringsdatum": "2024-02-28"
    },
    {
        "kungorelseid": "K149129/24",
        "uppgiftslamnare": "Bolagsverket",
        "kungorelsetyp": "Aktiebolagsregistret",
        "personOrgnummer": "",
        "namn": "Happie Art & Consulting AB",
        "publiceringsdatum": "2024-02-28"
    },
    {
        "kungorelseid": "K149197/24",
        "uppgiftslamnare": "Bolagsverket",
        "kungorelsetyp": "Aktiebolagsregistret",
        "personOrgnummer": "",
        "namn": "Ledarfokus Stockholm AB",
        "publiceringsdatum": "2024-02-28"
    },
    {
        "kungorelseid": "K149200/24",
        "uppgiftslamnare": "Bolagsverket",
        "kungorelsetyp": "Aktiebolagsregistret",
        "personOrgnummer": "",
        "namn": "TH Norden AB",
        "publiceringsdatum": "2024-02-28"
    },
    {
        "kungorelseid": "K149204/24",
        "uppgiftslamnare": "Bolagsverket",
        "kungorelsetyp": "Aktiebolagsregistret",
        "personOrgnummer": "",
        "namn": "RewireMe AB",
        "publiceringsdatum": "2024-02-28"
    },
    {
        "kungorelseid": "K149238/24",
        "uppgiftslamnare": "Bolagsverket",
        "kungorelsetyp": "Aktiebolagsregistret",
        "personOrgnummer": "",
        "namn": "AddWisdom AB",
        "publiceringsdatum": "2024-02-28"
    },
    {
        "kungorelseid": "K148751/24",
        "uppgiftslamnare": "Bolagsverket",
        "kungorelsetyp": "Aktiebolagsregistret",
        "personOrgnummer": "",
        "namn": "NYA Redovisning i Sverige AB",
        "publiceringsdatum": "2024-02-28"
    },
    {
        "kungorelseid": "K149295/24",
        "uppgiftslamnare": "Bolagsverket",
        "kungorelsetyp": "Aktiebolagsregistret",
        "personOrgnummer": "",
        "namn": "X Pile AB",
        "publiceringsdatum": "2024-02-28"
    },
    {
        "kungorelseid": "K149299/24",
        "uppgiftslamnare": "Bolagsverket",
        "kungorelsetyp": "Aktiebolagsregistret",
        "personOrgnummer": "",
        "namn": "Slutkl\u00e4mmen TMSEP242 AB",
        "publiceringsdatum": "2024-02-28"
    },
    {
        "kungorelseid": "K149303/24",
        "uppgiftslamnare": "Bolagsverket",
        "kungorelsetyp": "Aktiebolagsregistret",
        "personOrgnummer": "",
        "namn": "Sverker & Sverker AB",
        "publiceringsdatum": "2024-02-28"
    },
    {
        "kungorelseid": "K149310/24",
        "uppgiftslamnare": "Bolagsverket",
        "kungorelsetyp": "Aktiebolagsregistret",
        "personOrgnummer": "",
        "namn": "Swedish Renewables SPV 3 AB",
        "publiceringsdatum": "2024-02-28"
    },
    {
        "kungorelseid": "K148762/24",
        "uppgiftslamnare": "Bolagsverket",
        "kungorelsetyp": "Aktiebolagsregistret",
        "personOrgnummer": "",
        "namn": "Apricot Assistans AB",
        "publiceringsdatum": "2024-02-28"
    },
    {
        "kungorelseid": "K149315/24",
        "uppgiftslamnare": "Bolagsverket",
        "kungorelsetyp": "Aktiebolagsregistret",
        "personOrgnummer": "",
        "namn": "Klingspor Architects AB",
        "publiceringsdatum": "2024-02-28"
    },
    {
        "kungorelseid": "K149319/24",
        "uppgiftslamnare": "Bolagsverket",
        "kungorelsetyp": "Aktiebolagsregistret",
        "personOrgnummer": "",
        "namn": "Delinder Event och Konsult AB",
        "publiceringsdatum": "2024-02-28"
    },
    {
        "kungorelseid": "K149322/24",
        "uppgiftslamnare": "Bolagsverket",
        "kungorelsetyp": "Aktiebolagsregistret",
        "personOrgnummer": "",
        "namn": "Munkevik fastigheter invest AB",
        "publiceringsdatum": "2024-02-28"
    },
    {
        "kungorelseid": "K149324/24",
        "uppgiftslamnare": "Bolagsverket",
        "kungorelsetyp": "Aktiebolagsregistret",
        "personOrgnummer": "",
        "namn": "PAOZ AB",
        "publiceringsdatum": "2024-02-28"
    },
    {
        "kungorelseid": "K149330/24",
        "uppgiftslamnare": "Bolagsverket",
        "kungorelsetyp": "Aktiebolagsregistret",
        "personOrgnummer": "",
        "namn": "Emelie Dahlin AB",
        "publiceringsdatum": "2024-02-28"
    },
    {
        "kungorelseid": "K149333/24",
        "uppgiftslamnare": "Bolagsverket",
        "kungorelsetyp": "Aktiebolagsregistret",
        "personOrgnummer": "",
        "namn": "Myrberget Markutveckling 2 AB",
        "publiceringsdatum": "2024-02-28"
    },
    {
        "kungorelseid": "K148798/24",
        "uppgiftslamnare": "Bolagsverket",
        "kungorelsetyp": "Aktiebolagsregistret",
        "personOrgnummer": "",
        "namn": "Norrtex Bygg AB",
        "publiceringsdatum": "2024-02-28"
    },
    {
        "kungorelseid": "K149336/24",
        "uppgiftslamnare": "Bolagsverket",
        "kungorelsetyp": "Aktiebolagsregistret",
        "personOrgnummer": "",
        "namn": "Flowtract AB",
        "publiceringsdatum": "2024-02-28"
    },
    {
        "kungorelseid": "K149339/24",
        "uppgiftslamnare": "Bolagsverket",
        "kungorelsetyp": "Aktiebolagsregistret",
        "personOrgnummer": "",
        "namn": "H\u00f6gbonden Lighthouse AB",
        "publiceringsdatum": "2024-02-28"
    },
    {
        "kungorelseid": "K149343/24",
        "uppgiftslamnare": "Bolagsverket",
        "kungorelsetyp": "Aktiebolagsregistret",
        "personOrgnummer": "",
        "namn": "EF djursjukv\u00e5rd AB",
        "publiceringsdatum": "2024-02-28"
    },
    {
        "kungorelseid": "K149345/24",
        "uppgiftslamnare": "Bolagsverket",
        "kungorelsetyp": "Aktiebolagsregistret",
        "personOrgnummer": "",
        "namn": "Vilco Group AB",
        "publiceringsdatum": "2024-02-28"
    },
    {
        "kungorelseid": "K149384/24",
        "uppgiftslamnare": "Bolagsverket",
        "kungorelsetyp": "Aktiebolagsregistret",
        "personOrgnummer": "",
        "namn": "Seger & Son AB",
        "publiceringsdatum": "2024-02-28"
    },
    {
        "kungorelseid": "K149386/24",
        "uppgiftslamnare": "Bolagsverket",
        "kungorelsetyp": "Aktiebolagsregistret",
        "personOrgnummer": "",
        "namn": "David Nabavi AB",
        "publiceringsdatum": "2024-02-28"
    },
    {
        "kungorelseid": "K148813/24",
        "uppgiftslamnare": "Bolagsverket",
        "kungorelsetyp": "Aktiebolagsregistret",
        "personOrgnummer": "",
        "namn": "AMT \u00c5keri AB",
        "publiceringsdatum": "2024-02-28"
    },
    {
        "kungorelseid": "K149399/24",
        "uppgiftslamnare": "Bolagsverket",
        "kungorelsetyp": "Aktiebolagsregistret",
        "personOrgnummer": "",
        "namn": "Chocron Interim AB",
        "publiceringsdatum": "2024-02-28"
    },
    {
        "kungorelseid": "K149400/24",
        "uppgiftslamnare": "Bolagsverket",
        "kungorelsetyp": "Aktiebolagsregistret",
        "personOrgnummer": "",
        "namn": "Hppnss Real Estate AB",
        "publiceringsdatum": "2024-02-28"
    },
    {
        "kungorelseid": "K149416/24",
        "uppgiftslamnare": "Bolagsverket",
        "kungorelsetyp": "Aktiebolagsregistret",
        "personOrgnummer": "",
        "namn": "C Assistans AB",
        "publiceringsdatum": "2024-02-28"
    },
    {
        "kungorelseid": "K149417/24",
        "uppgiftslamnare": "Bolagsverket",
        "kungorelsetyp": "Aktiebolagsregistret",
        "personOrgnummer": "",
        "namn": "Dules Bygg & Mark AB",
        "publiceringsdatum": "2024-02-28"
    },
    {
        "kungorelseid": "K149419/24",
        "uppgiftslamnare": "Bolagsverket",
        "kungorelsetyp": "Aktiebolagsregistret",
        "personOrgnummer": "",
        "namn": "ATO STUDIOS AB",
        "publiceringsdatum": "2024-02-28"
    },
    {
        "kungorelseid": "K149435/24",
        "uppgiftslamnare": "Bolagsverket",
        "kungorelsetyp": "Aktiebolagsregistret",
        "personOrgnummer": "",
        "namn": "Grund- & Markkonsulter i Norr AB",
        "publiceringsdatum": "2024-02-28"
    },
    {
        "kungorelseid": "K147412/24",
        "uppgiftslamnare": "Bolagsverket",
        "kungorelsetyp": "Aktiebolagsregistret",
        "personOrgnummer": "",
        "namn": "SM Management & Consulting AB",
        "publiceringsdatum": "2024-02-28"
    },
    {
        "kungorelseid": "K150675/24",
        "uppgiftslamnare": "Bolagsverket",
        "kungorelsetyp": "Aktiebolagsregistret",
        "personOrgnummer": "",
        "namn": "Wint Startup 1233 AB",
        "publiceringsdatum": "2024-02-28"
    },
    {
        "kungorelseid": "K150677/24",
        "uppgiftslamnare": "Bolagsverket",
        "kungorelsetyp": "Aktiebolagsregistret",
        "personOrgnummer": "",
        "namn": "Wint Startup 1235 AB",
        "publiceringsdatum": "2024-02-28"
    },
    {
        "kungorelseid": "K149471/24",
        "uppgiftslamnare": "Bolagsverket",
        "kungorelsetyp": "Aktiebolagsregistret",
        "personOrgnummer": "",
        "namn": "Darodo AB",
        "publiceringsdatum": "2024-02-28"
    },
    {
        "kungorelseid": "K149476/24",
        "uppgiftslamnare": "Bolagsverket",
        "kungorelsetyp": "Aktiebolagsregistret",
        "personOrgnummer": "",
        "namn": "Swedfair AB",
        "publiceringsdatum": "2024-02-28"
    },
    {
        "kungorelseid": "K149489/24",
        "uppgiftslamnare": "Bolagsverket",
        "kungorelsetyp": "Aktiebolagsregistret",
        "personOrgnummer": "",
        "namn": "ODK People & Payroll AB",
        "publiceringsdatum": "2024-02-28"
    },
    {
        "kungorelseid": "K149492/24",
        "uppgiftslamnare": "Bolagsverket",
        "kungorelsetyp": "Aktiebolagsregistret",
        "personOrgnummer": "",
        "namn": "Haga Creative AB",
        "publiceringsdatum": "2024-02-28"
    },
    {
        "kungorelseid": "K149506/24",
        "uppgiftslamnare": "Bolagsverket",
        "kungorelsetyp": "Aktiebolagsregistret",
        "personOrgnummer": "",
        "namn": "Camilla Holm AB",
        "publiceringsdatum": "2024-02-28"
    },
    {
        "kungorelseid": "K149509/24",
        "uppgiftslamnare": "Bolagsverket",
        "kungorelsetyp": "Aktiebolagsregistret",
        "personOrgnummer": "",
        "namn": "Gustav Aldin Fotograf AB",
        "publiceringsdatum": "2024-02-28"
    },
    {
        "kungorelseid": "K149535/24",
        "uppgiftslamnare": "Bolagsverket",
        "kungorelsetyp": "Aktiebolagsregistret",
        "personOrgnummer": "",
        "namn": "NICMA Projekt & Utbildningskonsulten AB",
        "publiceringsdatum": "2024-02-28"
    },
    {
        "kungorelseid": "K149542/24",
        "uppgiftslamnare": "Bolagsverket",
        "kungorelsetyp": "Aktiebolagsregistret",
        "personOrgnummer": "",
        "namn": "Mark och anl\u00e4ggnings service Styrsta AB",
        "publiceringsdatum": "2024-02-28"
    },
    {
        "kungorelseid": "K149547/24",
        "uppgiftslamnare": "Bolagsverket",
        "kungorelsetyp": "Aktiebolagsregistret",
        "personOrgnummer": "",
        "namn": "Aventix Group AB",
        "publiceringsdatum": "2024-02-28"
    },
    {
        "kungorelseid": "K149550/24",
        "uppgiftslamnare": "Bolagsverket",
        "kungorelsetyp": "Aktiebolagsregistret",
        "personOrgnummer": "",
        "namn": "Lamadaya E-commerce AB",
        "publiceringsdatum": "2024-02-28"
    },
    {
        "kungorelseid": "K149561/24",
        "uppgiftslamnare": "Bolagsverket",
        "kungorelsetyp": "Aktiebolagsregistret",
        "personOrgnummer": "",
        "namn": "F Nordstr\u00f6m Food & Beverage AB",
        "publiceringsdatum": "2024-02-28"
    },
    {
        "kungorelseid": "K149564/24",
        "uppgiftslamnare": "Bolagsverket",
        "kungorelsetyp": "Aktiebolagsregistret",
        "personOrgnummer": "",
        "namn": "Byggkonsult G\u00f6ran Andersson p\u00e5 Gotland AB",
        "publiceringsdatum": "2024-02-28"
    },
    {
        "kungorelseid": "K149567/24",
        "uppgiftslamnare": "Bolagsverket",
        "kungorelsetyp": "Aktiebolagsregistret",
        "personOrgnummer": "",
        "namn": "Reinius Ejvinsson Design AB",
        "publiceringsdatum": "2024-02-28"
    },
    {
        "kungorelseid": "K149569/24",
        "uppgiftslamnare": "Bolagsverket",
        "kungorelsetyp": "Aktiebolagsregistret",
        "personOrgnummer": "",
        "namn": "WNE AB",
        "publiceringsdatum": "2024-02-28"
    },
    {
        "kungorelseid": "K149571/24",
        "uppgiftslamnare": "Bolagsverket",
        "kungorelsetyp": "Aktiebolagsregistret",
        "personOrgnummer": "",
        "namn": "Magnus Lid\u00e9n Karl AB",
        "publiceringsdatum": "2024-02-28"
    },
    {
        "kungorelseid": "K149586/24",
        "uppgiftslamnare": "Bolagsverket",
        "kungorelsetyp": "Aktiebolagsregistret",
        "personOrgnummer": "",
        "namn": "Biovitas Fuels AB",
        "publiceringsdatum": "2024-02-28"
    },
    {
        "kungorelseid": "K149589/24",
        "uppgiftslamnare": "Bolagsverket",
        "kungorelsetyp": "Aktiebolagsregistret",
        "personOrgnummer": "",
        "namn": "Dahlgren Tr\u00e4design AB",
        "publiceringsdatum": "2024-02-28"
    },
    {
        "kungorelseid": "K149591/24",
        "uppgiftslamnare": "Bolagsverket",
        "kungorelsetyp": "Aktiebolagsregistret",
        "personOrgnummer": "",
        "namn": "Ankord Consulting AB",
        "publiceringsdatum": "2024-02-28"
    },
    {
        "kungorelseid": "K149594/24",
        "uppgiftslamnare": "Bolagsverket",
        "kungorelsetyp": "Aktiebolagsregistret",
        "personOrgnummer": "",
        "namn": "S\u00f6derberg Bygg & Fastighet AB",
        "publiceringsdatum": "2024-02-28"
    },
    {
        "kungorelseid": "K149599/24",
        "uppgiftslamnare": "Bolagsverket",
        "kungorelsetyp": "Aktiebolagsregistret",
        "personOrgnummer": "",
        "namn": "Emelie Edman AB",
        "publiceringsdatum": "2024-02-28"
    },
    {
        "kungorelseid": "K149607/24",
        "uppgiftslamnare": "Bolagsverket",
        "kungorelsetyp": "Aktiebolagsregistret",
        "personOrgnummer": "",
        "namn": "Vedia AB",
        "publiceringsdatum": "2024-02-28"
    },
    {
        "kungorelseid": "K149610/24",
        "uppgiftslamnare": "Bolagsverket",
        "kungorelsetyp": "Aktiebolagsregistret",
        "personOrgnummer": "",
        "namn": "NEAD EL & Fastighetsservice AB",
        "publiceringsdatum": "2024-02-28"
    },
    {
        "kungorelseid": "K149618/24",
        "uppgiftslamnare": "Bolagsverket",
        "kungorelsetyp": "Aktiebolagsregistret",
        "personOrgnummer": "",
        "namn": "KTM Montage AB",
        "publiceringsdatum": "2024-02-28"
    },
    {
        "kungorelseid": "K149439/24",
        "uppgiftslamnare": "Bolagsverket",
        "kungorelsetyp": "Aktiebolagsregistret",
        "personOrgnummer": "",
        "namn": "Dont step on my boots AB",
        "publiceringsdatum": "2024-02-28"
    },
    {
        "kungorelseid": "K148553/24",
        "uppgiftslamnare": "Bolagsverket",
        "kungorelsetyp": "Aktiebolagsregistret",
        "personOrgnummer": "",
        "namn": "Macadam Automotive Sweden AB",
        "publiceringsdatum": "2024-02-28"
    },
    {
        "kungorelseid": "K148655/24",
        "uppgiftslamnare": "Bolagsverket",
        "kungorelsetyp": "Aktiebolagsregistret",
        "personOrgnummer": "",
        "namn": "E-Kungen AB",
        "publiceringsdatum": "2024-02-28"
    },
    {
        "kungorelseid": "K148706/24",
        "uppgiftslamnare": "Bolagsverket",
        "kungorelsetyp": "Aktiebolagsregistret",
        "personOrgnummer": "",
        "namn": "Nybyggt i norr AB",
        "publiceringsdatum": "2024-02-28"
    },
    {
        "kungorelseid": "K148721/24",
        "uppgiftslamnare": "Bolagsverket",
        "kungorelsetyp": "Aktiebolagsregistret",
        "personOrgnummer": "",
        "namn": "TUNING Precision AB",
        "publiceringsdatum": "2024-02-28"
    },
    {
        "kungorelseid": "K148739/24",
        "uppgiftslamnare": "Bolagsverket",
        "kungorelsetyp": "Aktiebolagsregistret",
        "personOrgnummer": "",
        "namn": "GRATIA SVERIGE AB",
        "publiceringsdatum": "2024-02-28"
    },
    {
        "kungorelseid": "K148559/24",
        "uppgiftslamnare": "Bolagsverket",
        "kungorelsetyp": "Aktiebolagsregistret",
        "personOrgnummer": "",
        "namn": "BioFert AB",
        "publiceringsdatum": "2024-02-28"
    },
    {
        "kungorelseid": "K148752/24",
        "uppgiftslamnare": "Bolagsverket",
        "kungorelsetyp": "Aktiebolagsregistret",
        "personOrgnummer": "",
        "namn": "Tidi Labs AB",
        "publiceringsdatum": "2024-02-28"
    },
    {
        "kungorelseid": "K148849/24",
        "uppgiftslamnare": "Bolagsverket",
        "kungorelsetyp": "Aktiebolagsregistret",
        "personOrgnummer": "",
        "namn": "Repeto AB",
        "publiceringsdatum": "2024-02-28"
    },
    {
        "kungorelseid": "K148852/24",
        "uppgiftslamnare": "Bolagsverket",
        "kungorelsetyp": "Aktiebolagsregistret",
        "personOrgnummer": "",
        "namn": "Kims Bil & Motor AB",
        "publiceringsdatum": "2024-02-28"
    },
    {
        "kungorelseid": "K148869/24",
        "uppgiftslamnare": "Bolagsverket",
        "kungorelsetyp": "Aktiebolagsregistret",
        "personOrgnummer": "",
        "namn": "Exalted AB",
        "publiceringsdatum": "2024-02-28"
    },
    {
        "kungorelseid": "K148763/24",
        "uppgiftslamnare": "Bolagsverket",
        "kungorelsetyp": "Aktiebolagsregistret",
        "personOrgnummer": "",
        "namn": "JRP Konsult AB",
        "publiceringsdatum": "2024-02-28"
    },
    {
        "kungorelseid": "K148809/24",
        "uppgiftslamnare": "Bolagsverket",
        "kungorelsetyp": "Aktiebolagsregistret",
        "personOrgnummer": "",
        "namn": "CCT Aktiebolag",
        "publiceringsdatum": "2024-02-28"
    },
    {
        "kungorelseid": "K149211/24",
        "uppgiftslamnare": "Bolagsverket",
        "kungorelsetyp": "Aktiebolagsregistret",
        "personOrgnummer": "",
        "namn": "Baume Essentials AB",
        "publiceringsdatum": "2024-02-28"
    },
    {
        "kungorelseid": "K149298/24",
        "uppgiftslamnare": "Bolagsverket",
        "kungorelsetyp": "Aktiebolagsregistret",
        "personOrgnummer": "",
        "namn": "Slutkl\u00e4mmen TMSEP241 AB",
        "publiceringsdatum": "2024-02-28"
    },
    {
        "kungorelseid": "K149223/24",
        "uppgiftslamnare": "Bolagsverket",
        "kungorelsetyp": "Aktiebolagsregistret",
        "personOrgnummer": "",
        "namn": "B&B Teknik AB",
        "publiceringsdatum": "2024-02-28"
    },
    {
        "kungorelseid": "K149316/24",
        "uppgiftslamnare": "Bolagsverket",
        "kungorelsetyp": "Aktiebolagsregistret",
        "personOrgnummer": "",
        "namn": "Maja Bud AB",
        "publiceringsdatum": "2024-02-28"
    },
    {
        "kungorelseid": "K149325/24",
        "uppgiftslamnare": "Bolagsverket",
        "kungorelsetyp": "Aktiebolagsregistret",
        "personOrgnummer": "",
        "namn": "Stories by Mia AB",
        "publiceringsdatum": "2024-02-28"
    },
    {
        "kungorelseid": "K149334/24",
        "uppgiftslamnare": "Bolagsverket",
        "kungorelsetyp": "Aktiebolagsregistret",
        "personOrgnummer": "",
        "namn": "Freed Spicemix consulting AB",
        "publiceringsdatum": "2024-02-28"
    },
    {
        "kungorelseid": "K149344/24",
        "uppgiftslamnare": "Bolagsverket",
        "kungorelsetyp": "Aktiebolagsregistret",
        "personOrgnummer": "",
        "namn": "MAX Training Trading AB",
        "publiceringsdatum": "2024-02-28"
    },
    {
        "kungorelseid": "K149359/24",
        "uppgiftslamnare": "Bolagsverket",
        "kungorelsetyp": "Aktiebolagsregistret",
        "personOrgnummer": "",
        "namn": "Vinylhem AB",
        "publiceringsdatum": "2024-02-28"
    },
    {
        "kungorelseid": "K149363/24",
        "uppgiftslamnare": "Bolagsverket",
        "kungorelsetyp": "Aktiebolagsregistret",
        "personOrgnummer": "",
        "namn": "Fang Invest AB",
        "publiceringsdatum": "2024-02-28"
    },
    {
        "kungorelseid": "K149365/24",
        "uppgiftslamnare": "Bolagsverket",
        "kungorelsetyp": "Aktiebolagsregistret",
        "personOrgnummer": "",
        "namn": "L\u00e5dans Bryggeri AB",
        "publiceringsdatum": "2024-02-28"
    },
    {
        "kungorelseid": "K149369/24",
        "uppgiftslamnare": "Bolagsverket",
        "kungorelsetyp": "Aktiebolagsregistret",
        "personOrgnummer": "",
        "namn": "RGVENT AB",
        "publiceringsdatum": "2024-02-28"
    },
    {
        "kungorelseid": "K149301/24",
        "uppgiftslamnare": "Bolagsverket",
        "kungorelsetyp": "Aktiebolagsregistret",
        "personOrgnummer": "",
        "namn": "Slutkl\u00e4mmen 24e1 AB",
        "publiceringsdatum": "2024-02-28"
    },
    {
        "kungorelseid": "K149327/24",
        "uppgiftslamnare": "Bolagsverket",
        "kungorelsetyp": "Aktiebolagsregistret",
        "personOrgnummer": "",
        "namn": "Food4P AB",
        "publiceringsdatum": "2024-02-28"
    },
    {
        "kungorelseid": "K149331/24",
        "uppgiftslamnare": "Bolagsverket",
        "kungorelsetyp": "Aktiebolagsregistret",
        "personOrgnummer": "",
        "namn": "Myrberget Markutveckling 3 AB",
        "publiceringsdatum": "2024-02-28"
    },
    {
        "kungorelseid": "K149346/24",
        "uppgiftslamnare": "Bolagsverket",
        "kungorelsetyp": "Aktiebolagsregistret",
        "personOrgnummer": "",
        "namn": "NA Ros\u00e9n Consulting Aktiebolag",
        "publiceringsdatum": "2024-02-28"
    },
    {
        "kungorelseid": "K149371/24",
        "uppgiftslamnare": "Bolagsverket",
        "kungorelsetyp": "Aktiebolagsregistret",
        "personOrgnummer": "",
        "namn": "DM Bilar AB",
        "publiceringsdatum": "2024-02-28"
    },
    {
        "kungorelseid": "K149375/24",
        "uppgiftslamnare": "Bolagsverket",
        "kungorelsetyp": "Aktiebolagsregistret",
        "personOrgnummer": "",
        "namn": "Fastighetsbolaget Pepparv\u00e4gen AB",
        "publiceringsdatum": "2024-02-28"
    },
    {
        "kungorelseid": "K149453/24",
        "uppgiftslamnare": "Bolagsverket",
        "kungorelsetyp": "Aktiebolagsregistret",
        "personOrgnummer": "",
        "namn": "Szynszecki Capital Holding AB",
        "publiceringsdatum": "2024-02-28"
    },
    {
        "kungorelseid": "K149460/24",
        "uppgiftslamnare": "Bolagsverket",
        "kungorelsetyp": "Aktiebolagsregistret",
        "personOrgnummer": "",
        "namn": "Bost\u00e4llet i Ask Aktiebolag",
        "publiceringsdatum": "2024-02-28"
    },
    {
        "kungorelseid": "K149483/24",
        "uppgiftslamnare": "Bolagsverket",
        "kungorelsetyp": "Aktiebolagsregistret",
        "personOrgnummer": "",
        "namn": "SENSOL AB",
        "publiceringsdatum": "2024-02-28"
    },
    {
        "kungorelseid": "K149486/24",
        "uppgiftslamnare": "Bolagsverket",
        "kungorelsetyp": "Aktiebolagsregistret",
        "personOrgnummer": "",
        "namn": "AKTIEBOLAGET GUNNAR ARKITEKTER",
        "publiceringsdatum": "2024-02-28"
    },
    {
        "kungorelseid": "K149499/24",
        "uppgiftslamnare": "Bolagsverket",
        "kungorelsetyp": "Aktiebolagsregistret",
        "personOrgnummer": "",
        "namn": "Themo konsult AB",
        "publiceringsdatum": "2024-02-28"
    },
    {
        "kungorelseid": "K149502/24",
        "uppgiftslamnare": "Bolagsverket",
        "kungorelsetyp": "Aktiebolagsregistret",
        "personOrgnummer": "",
        "namn": "Conny Berglund Holding AB",
        "publiceringsdatum": "2024-02-28"
    },
    {
        "kungorelseid": "K149511/24",
        "uppgiftslamnare": "Bolagsverket",
        "kungorelsetyp": "Aktiebolagsregistret",
        "personOrgnummer": "",
        "namn": "LinellFaarvang AB",
        "publiceringsdatum": "2024-02-28"
    },
    {
        "kungorelseid": "K149523/24",
        "uppgiftslamnare": "Bolagsverket",
        "kungorelsetyp": "Aktiebolagsregistret",
        "personOrgnummer": "",
        "namn": "Niko-EL AB",
        "publiceringsdatum": "2024-02-28"
    },
    {
        "kungorelseid": "K150680/24",
        "uppgiftslamnare": "Bolagsverket",
        "kungorelsetyp": "Aktiebolagsregistret",
        "personOrgnummer": "",
        "namn": "Wint Startup 1237 AB",
        "publiceringsdatum": "2024-02-28"
    },
    {
        "kungorelseid": "K150683/24",
        "uppgiftslamnare": "Bolagsverket",
        "kungorelsetyp": "Aktiebolagsregistret",
        "personOrgnummer": "",
        "namn": "Wint Startup 1239 AB",
        "publiceringsdatum": "2024-02-28"
    },
    {
        "kungorelseid": "K150678/24",
        "uppgiftslamnare": "Bolagsverket",
        "kungorelsetyp": "Aktiebolagsregistret",
        "personOrgnummer": "",
        "namn": "Wint Startup 1236 AB",
        "publiceringsdatum": "2024-02-28"
    },
    {
        "kungorelseid": "K150681/24",
        "uppgiftslamnare": "Bolagsverket",
        "kungorelsetyp": "Aktiebolagsregistret",
        "personOrgnummer": "",
        "namn": "Wint Startup 1238 AB",
        "publiceringsdatum": "2024-02-28"
    },
    {
        "kungorelseid": "K150682/24",
        "uppgiftslamnare": "Bolagsverket",
        "kungorelsetyp": "Aktiebolagsregistret",
        "personOrgnummer": "",
        "namn": "Wint Startup 1230 AB",
        "publiceringsdatum": "2024-02-28"
    },
    {
        "kungorelseid": "K150684/24",
        "uppgiftslamnare": "Bolagsverket",
        "kungorelsetyp": "Aktiebolagsregistret",
        "personOrgnummer": "",
        "namn": "Wint Startup 1231 AB",
        "publiceringsdatum": "2024-02-28"
    },
    {
        "kungorelseid": "K148577/24",
        "uppgiftslamnare": "Bolagsverket",
        "kungorelsetyp": "Aktiebolagsregistret",
        "personOrgnummer": "",
        "namn": "G Ramsvik AB",
        "publiceringsdatum": "2024-02-28"
    },
    {
        "kungorelseid": "K148634/24",
        "uppgiftslamnare": "Bolagsverket",
        "kungorelsetyp": "Aktiebolagsregistret",
        "personOrgnummer": "",
        "namn": "MaPi F\u00f6rvaltnings AB",
        "publiceringsdatum": "2024-02-28"
    },
    {
        "kungorelseid": "K148698/24",
        "uppgiftslamnare": "Bolagsverket",
        "kungorelsetyp": "Aktiebolagsregistret",
        "personOrgnummer": "",
        "namn": "FM kliniken i Sverige AB",
        "publiceringsdatum": "2024-02-28"
    },
    {
        "kungorelseid": "K148700/24",
        "uppgiftslamnare": "Bolagsverket",
        "kungorelsetyp": "Aktiebolagsregistret",
        "personOrgnummer": "",
        "namn": "Atelj\u00e9ns Livs AB",
        "publiceringsdatum": "2024-02-28"
    },
    {
        "kungorelseid": "K148719/24",
        "uppgiftslamnare": "Bolagsverket",
        "kungorelsetyp": "Aktiebolagsregistret",
        "personOrgnummer": "",
        "namn": "Jasmine Soufi AB",
        "publiceringsdatum": "2024-02-28"
    },
    {
        "kungorelseid": "K150508/24",
        "uppgiftslamnare": "Bolagsverket",
        "kungorelsetyp": "Aktiebolagsregistret",
        "personOrgnummer": "",
        "namn": "Grundbulten 134475 AB",
        "publiceringsdatum": "2024-02-28"
    },
    {
        "kungorelseid": "K150510/24",
        "uppgiftslamnare": "Bolagsverket",
        "kungorelsetyp": "Aktiebolagsregistret",
        "personOrgnummer": "",
        "namn": "Grundbulten 134499 AB",
        "publiceringsdatum": "2024-02-28"
    },
    {
        "kungorelseid": "K150512/24",
        "uppgiftslamnare": "Bolagsverket",
        "kungorelsetyp": "Aktiebolagsregistret",
        "personOrgnummer": "",
        "namn": "Grundbulten 134497 AB",
        "publiceringsdatum": "2024-02-28"
    },
    {
        "kungorelseid": "K150516/24",
        "uppgiftslamnare": "Bolagsverket",
        "kungorelsetyp": "Aktiebolagsregistret",
        "personOrgnummer": "",
        "namn": "Grundbulten 134479 AB",
        "publiceringsdatum": "2024-02-28"
    },
    {
        "kungorelseid": "K149447/24",
        "uppgiftslamnare": "Bolagsverket",
        "kungorelsetyp": "Aktiebolagsregistret",
        "personOrgnummer": "",
        "namn": "Backatorp Bygg AB",
        "publiceringsdatum": "2024-02-28"
    },
    {
        "kungorelseid": "K150518/24",
        "uppgiftslamnare": "Bolagsverket",
        "kungorelsetyp": "Aktiebolagsregistret",
        "personOrgnummer": "",
        "namn": "Grundbulten 134477 AB",
        "publiceringsdatum": "2024-02-28"
    },
    {
        "kungorelseid": "K150520/24",
        "uppgiftslamnare": "Bolagsverket",
        "kungorelsetyp": "Aktiebolagsregistret",
        "personOrgnummer": "",
        "namn": "Grundbulten 134480 AB",
        "publiceringsdatum": "2024-02-28"
    },
    {
        "kungorelseid": "K149454/24",
        "uppgiftslamnare": "Bolagsverket",
        "kungorelsetyp": "Aktiebolagsregistret",
        "personOrgnummer": "",
        "namn": "Acudea holding AB",
        "publiceringsdatum": "2024-02-28"
    },
    {
        "kungorelseid": "K149457/24",
        "uppgiftslamnare": "Bolagsverket",
        "kungorelsetyp": "Aktiebolagsregistret",
        "personOrgnummer": "",
        "namn": "AeroLens Productions AB",
        "publiceringsdatum": "2024-02-28"
    },
    {
        "kungorelseid": "K150522/24",
        "uppgiftslamnare": "Bolagsverket",
        "kungorelsetyp": "Aktiebolagsregistret",
        "personOrgnummer": "",
        "namn": "Grundbulten 134486 AB",
        "publiceringsdatum": "2024-02-28"
    },
    {
        "kungorelseid": "K150524/24",
        "uppgiftslamnare": "Bolagsverket",
        "kungorelsetyp": "Aktiebolagsregistret",
        "personOrgnummer": "",
        "namn": "Grundbulten 134484 AB",
        "publiceringsdatum": "2024-02-28"
    },
    {
        "kungorelseid": "K149459/24",
        "uppgiftslamnare": "Bolagsverket",
        "kungorelsetyp": "Aktiebolagsregistret",
        "personOrgnummer": "",
        "namn": "Chishiki AB",
        "publiceringsdatum": "2024-02-28"
    },
    {
        "kungorelseid": "K149464/24",
        "uppgiftslamnare": "Bolagsverket",
        "kungorelsetyp": "Aktiebolagsregistret",
        "personOrgnummer": "",
        "namn": "Klinkhammer Consulting AB",
        "publiceringsdatum": "2024-02-28"
    },
    {
        "kungorelseid": "K149519/24",
        "uppgiftslamnare": "Bolagsverket",
        "kungorelsetyp": "Aktiebolagsregistret",
        "personOrgnummer": "",
        "namn": "VACO SKILLS AB",
        "publiceringsdatum": "2024-02-28"
    },
    {
        "kungorelseid": "K149528/24",
        "uppgiftslamnare": "Bolagsverket",
        "kungorelsetyp": "Aktiebolagsregistret",
        "personOrgnummer": "",
        "namn": "M\u00e5larsson AB",
        "publiceringsdatum": "2024-02-28"
    },
    {
        "kungorelseid": "K150527/24",
        "uppgiftslamnare": "Bolagsverket",
        "kungorelsetyp": "Aktiebolagsregistret",
        "personOrgnummer": "",
        "namn": "Grundbulten 134490 AB",
        "publiceringsdatum": "2024-02-28"
    },
    {
        "kungorelseid": "K150529/24",
        "uppgiftslamnare": "Bolagsverket",
        "kungorelsetyp": "Aktiebolagsregistret",
        "personOrgnummer": "",
        "namn": "Grundbulten 134488 AB",
        "publiceringsdatum": "2024-02-28"
    },
    {
        "kungorelseid": "K149466/24",
        "uppgiftslamnare": "Bolagsverket",
        "kungorelsetyp": "Aktiebolagsregistret",
        "personOrgnummer": "",
        "namn": "KVARTERSKOCK AB",
        "publiceringsdatum": "2024-02-28"
    },
    {
        "kungorelseid": "K149470/24",
        "uppgiftslamnare": "Bolagsverket",
        "kungorelsetyp": "Aktiebolagsregistret",
        "personOrgnummer": "",
        "namn": "Claessons Mark o Bygg AB",
        "publiceringsdatum": "2024-02-28"
    },
    {
        "kungorelseid": "K149536/24",
        "uppgiftslamnare": "Bolagsverket",
        "kungorelsetyp": "Aktiebolagsregistret",
        "personOrgnummer": "",
        "namn": "LeSerene AB",
        "publiceringsdatum": "2024-02-28"
    },
    {
        "kungorelseid": "K149541/24",
        "uppgiftslamnare": "Bolagsverket",
        "kungorelsetyp": "Aktiebolagsregistret",
        "personOrgnummer": "",
        "namn": "KONZOL AB",
        "publiceringsdatum": "2024-02-28"
    },
    {
        "kungorelseid": "K150532/24",
        "uppgiftslamnare": "Bolagsverket",
        "kungorelsetyp": "Aktiebolagsregistret",
        "personOrgnummer": "",
        "namn": "Grundbulten 134494 AB",
        "publiceringsdatum": "2024-02-28"
    },
    {
        "kungorelseid": "K150534/24",
        "uppgiftslamnare": "Bolagsverket",
        "kungorelsetyp": "Aktiebolagsregistret",
        "personOrgnummer": "",
        "namn": "Grundbulten 134492 AB",
        "publiceringsdatum": "2024-02-28"
    },
    {
        "kungorelseid": "K149472/24",
        "uppgiftslamnare": "Bolagsverket",
        "kungorelsetyp": "Aktiebolagsregistret",
        "personOrgnummer": "",
        "namn": "Non La AB",
        "publiceringsdatum": "2024-02-28"
    },
    {
        "kungorelseid": "K149479/24",
        "uppgiftslamnare": "Bolagsverket",
        "kungorelsetyp": "Aktiebolagsregistret",
        "personOrgnummer": "",
        "namn": "Anna Thelander AB",
        "publiceringsdatum": "2024-02-28"
    },
    {
        "kungorelseid": "K149548/24",
        "uppgiftslamnare": "Bolagsverket",
        "kungorelsetyp": "Aktiebolagsregistret",
        "personOrgnummer": "",
        "namn": "Ljung Management & Consulting AB",
        "publiceringsdatum": "2024-02-28"
    },
    {
        "kungorelseid": "K149549/24",
        "uppgiftslamnare": "Bolagsverket",
        "kungorelsetyp": "Aktiebolagsregistret",
        "personOrgnummer": "",
        "namn": "Ross Fotv\u00e5rdsklink AB",
        "publiceringsdatum": "2024-02-28"
    },
    {
        "kungorelseid": "K149481/24",
        "uppgiftslamnare": "Bolagsverket",
        "kungorelsetyp": "Aktiebolagsregistret",
        "personOrgnummer": "",
        "namn": "ENY media AB",
        "publiceringsdatum": "2024-02-28"
    },
    {
        "kungorelseid": "K149485/24",
        "uppgiftslamnare": "Bolagsverket",
        "kungorelsetyp": "Aktiebolagsregistret",
        "personOrgnummer": "",
        "namn": "Arbetsro \u00d6stersund AB",
        "publiceringsdatum": "2024-02-28"
    },
    {
        "kungorelseid": "K149555/24",
        "uppgiftslamnare": "Bolagsverket",
        "kungorelsetyp": "Aktiebolagsregistret",
        "personOrgnummer": "",
        "namn": "The Notlanders AB",
        "publiceringsdatum": "2024-02-28"
    },
    {
        "kungorelseid": "K149557/24",
        "uppgiftslamnare": "Bolagsverket",
        "kungorelsetyp": "Aktiebolagsregistret",
        "personOrgnummer": "",
        "namn": "Urex AB",
        "publiceringsdatum": "2024-02-28"
    },
    {
        "kungorelseid": "K149488/24",
        "uppgiftslamnare": "Bolagsverket",
        "kungorelsetyp": "Aktiebolagsregistret",
        "personOrgnummer": "",
        "namn": "Orka energi AB",
        "publiceringsdatum": "2024-02-28"
    },
    {
        "kungorelseid": "K149494/24",
        "uppgiftslamnare": "Bolagsverket",
        "kungorelsetyp": "Aktiebolagsregistret",
        "personOrgnummer": "",
        "namn": "Ad&Ad AB",
        "publiceringsdatum": "2024-02-28"
    },
    {
        "kungorelseid": "K149770/24",
        "uppgiftslamnare": "Bolagsverket",
        "kungorelsetyp": "Aktiebolagsregistret",
        "personOrgnummer": "",
        "namn": "Vist Hyreshus AB",
        "publiceringsdatum": "2024-02-28"
    },
    {
        "kungorelseid": "K150638/24",
        "uppgiftslamnare": "Bolagsverket",
        "kungorelsetyp": "Aktiebolagsregistret",
        "personOrgnummer": "",
        "namn": "Forma 8268 AB",
        "publiceringsdatum": "2024-02-28"
    },
    {
        "kungorelseid": "K149500/24",
        "uppgiftslamnare": "Bolagsverket",
        "kungorelsetyp": "Aktiebolagsregistret",
        "personOrgnummer": "",
        "namn": "Isac J\u00f6nsson AB",
        "publiceringsdatum": "2024-02-28"
    },
    {
        "kungorelseid": "K149559/24",
        "uppgiftslamnare": "Bolagsverket",
        "kungorelsetyp": "Aktiebolagsregistret",
        "personOrgnummer": "",
        "namn": "Visionite V\u00e4ster\u00e5s AB",
        "publiceringsdatum": "2024-02-28"
    },
    {
        "kungorelseid": "K149563/24",
        "uppgiftslamnare": "Bolagsverket",
        "kungorelsetyp": "Aktiebolagsregistret",
        "personOrgnummer": "",
        "namn": "Bj\u00f6rndal consulting AB",
        "publiceringsdatum": "2024-02-28"
    },
    {
        "kungorelseid": "K150674/24",
        "uppgiftslamnare": "Bolagsverket",
        "kungorelsetyp": "Aktiebolagsregistret",
        "personOrgnummer": "",
        "namn": "Wint Startup 1232 AB",
        "publiceringsdatum": "2024-02-28"
    },
    {
        "kungorelseid": "K149568/24",
        "uppgiftslamnare": "Bolagsverket",
        "kungorelsetyp": "Aktiebolagsregistret",
        "personOrgnummer": "",
        "namn": "Fridriksson Ekonomi AB",
        "publiceringsdatum": "2024-02-28"
    },
    {
        "kungorelseid": "K149570/24",
        "uppgiftslamnare": "Bolagsverket",
        "kungorelsetyp": "Aktiebolagsregistret",
        "personOrgnummer": "",
        "namn": "G\u00e4llivare Entreprenad i Norr AB",
        "publiceringsdatum": "2024-02-28"
    },
    {
        "kungorelseid": "K150676/24",
        "uppgiftslamnare": "Bolagsverket",
        "kungorelsetyp": "Aktiebolagsregistret",
        "personOrgnummer": "",
        "namn": "Wint Startup 1234 AB",
        "publiceringsdatum": "2024-02-28"
    },
    {
        "kungorelseid": "K149504/24",
        "uppgiftslamnare": "Bolagsverket",
        "kungorelsetyp": "Aktiebolagsregistret",
        "personOrgnummer": "",
        "namn": "JL Timmerhus AB",
        "publiceringsdatum": "2024-02-28"
    },
    {
        "kungorelseid": "K149507/24",
        "uppgiftslamnare": "Bolagsverket",
        "kungorelsetyp": "Aktiebolagsregistret",
        "personOrgnummer": "",
        "namn": "Prayminder AB",
        "publiceringsdatum": "2024-02-28"
    },
    {
        "kungorelseid": "K149577/24",
        "uppgiftslamnare": "Bolagsverket",
        "kungorelsetyp": "Aktiebolagsregistret",
        "personOrgnummer": "",
        "namn": "Harling Capital Partners Aktiebolag",
        "publiceringsdatum": "2024-02-28"
    },
    {
        "kungorelseid": "K149510/24",
        "uppgiftslamnare": "Bolagsverket",
        "kungorelsetyp": "Aktiebolagsregistret",
        "personOrgnummer": "",
        "namn": "Softest AB",
        "publiceringsdatum": "2024-02-28"
    },
    {
        "kungorelseid": "K149512/24",
        "uppgiftslamnare": "Bolagsverket",
        "kungorelsetyp": "Aktiebolagsregistret",
        "personOrgnummer": "",
        "namn": "Wecab Stockholm AB",
        "publiceringsdatum": "2024-02-28"
    },
    {
        "kungorelseid": "K149584/24",
        "uppgiftslamnare": "Bolagsverket",
        "kungorelsetyp": "Aktiebolagsregistret",
        "personOrgnummer": "",
        "namn": "Sj\u00f6skogen Konsult AB",
        "publiceringsdatum": "2024-02-28"
    },
    {
        "kungorelseid": "K149587/24",
        "uppgiftslamnare": "Bolagsverket",
        "kungorelsetyp": "Aktiebolagsregistret",
        "personOrgnummer": "",
        "namn": "MoJo Fris\u00f6r AB",
        "publiceringsdatum": "2024-02-28"
    },
    {
        "kungorelseid": "K149514/24",
        "uppgiftslamnare": "Bolagsverket",
        "kungorelsetyp": "Aktiebolagsregistret",
        "personOrgnummer": "",
        "namn": "IM L\u00e4karkonsult AB",
        "publiceringsdatum": "2024-02-28"
    },
    {
        "kungorelseid": "K149517/24",
        "uppgiftslamnare": "Bolagsverket",
        "kungorelsetyp": "Aktiebolagsregistret",
        "personOrgnummer": "",
        "namn": "Millum Design AB",
        "publiceringsdatum": "2024-02-28"
    },
    {
        "kungorelseid": "K149590/24",
        "uppgiftslamnare": "Bolagsverket",
        "kungorelsetyp": "Aktiebolagsregistret",
        "personOrgnummer": "",
        "namn": "Biovitas Operations AB",
        "publiceringsdatum": "2024-02-28"
    },
    {
        "kungorelseid": "K149592/24",
        "uppgiftslamnare": "Bolagsverket",
        "kungorelsetyp": "Aktiebolagsregistret",
        "personOrgnummer": "",
        "namn": "OptiCell Solutions AB",
        "publiceringsdatum": "2024-02-28"
    },
    {
        "kungorelseid": "K150517/24",
        "uppgiftslamnare": "Bolagsverket",
        "kungorelsetyp": "Aktiebolagsregistret",
        "personOrgnummer": "",
        "namn": "Grundbulten 134482 AB",
        "publiceringsdatum": "2024-02-28"
    },
    {
        "kungorelseid": "K150519/24",
        "uppgiftslamnare": "Bolagsverket",
        "kungorelsetyp": "Aktiebolagsregistret",
        "personOrgnummer": "",
        "namn": "Grundbulten 134483 AB",
        "publiceringsdatum": "2024-02-28"
    },
    {
        "kungorelseid": "K149616/24",
        "uppgiftslamnare": "Bolagsverket",
        "kungorelsetyp": "Aktiebolagsregistret",
        "personOrgnummer": "",
        "namn": "Chokdee Fastighet AB",
        "publiceringsdatum": "2024-02-28"
    },
    {
        "kungorelseid": "K150509/24",
        "uppgiftslamnare": "Bolagsverket",
        "kungorelsetyp": "Aktiebolagsregistret",
        "personOrgnummer": "",
        "namn": "Grundbulten 134498 AB",
        "publiceringsdatum": "2024-02-28"
    },
    {
        "kungorelseid": "K150511/24",
        "uppgiftslamnare": "Bolagsverket",
        "kungorelsetyp": "Aktiebolagsregistret",
        "personOrgnummer": "",
        "namn": "Grundbulten 134496 AB",
        "publiceringsdatum": "2024-02-28"
    },
    {
        "kungorelseid": "K150521/24",
        "uppgiftslamnare": "Bolagsverket",
        "kungorelsetyp": "Aktiebolagsregistret",
        "personOrgnummer": "",
        "namn": "Grundbulten 134481 AB",
        "publiceringsdatum": "2024-02-28"
    },
    {
        "kungorelseid": "K150523/24",
        "uppgiftslamnare": "Bolagsverket",
        "kungorelsetyp": "Aktiebolagsregistret",
        "personOrgnummer": "",
        "namn": "Grundbulten 134487 AB",
        "publiceringsdatum": "2024-02-28"
    },
    {
        "kungorelseid": "K150530/24",
        "uppgiftslamnare": "Bolagsverket",
        "kungorelsetyp": "Aktiebolagsregistret",
        "personOrgnummer": "",
        "namn": "Grundbulten 134489 AB",
        "publiceringsdatum": "2024-02-28"
    },
    {
        "kungorelseid": "K150533/24",
        "uppgiftslamnare": "Bolagsverket",
        "kungorelsetyp": "Aktiebolagsregistret",
        "personOrgnummer": "",
        "namn": "Grundbulten 134495 AB",
        "publiceringsdatum": "2024-02-28"
    },
    {
        "kungorelseid": "K150513/24",
        "uppgiftslamnare": "Bolagsverket",
        "kungorelsetyp": "Aktiebolagsregistret",
        "personOrgnummer": "",
        "namn": "Grundbulten 134478 AB",
        "publiceringsdatum": "2024-02-28"
    },
    {
        "kungorelseid": "K150515/24",
        "uppgiftslamnare": "Bolagsverket",
        "kungorelsetyp": "Aktiebolagsregistret",
        "personOrgnummer": "",
        "namn": "Grundbulten 134476 AB",
        "publiceringsdatum": "2024-02-28"
    },
    {
        "kungorelseid": "K150525/24",
        "uppgiftslamnare": "Bolagsverket",
        "kungorelsetyp": "Aktiebolagsregistret",
        "personOrgnummer": "",
        "namn": "Grundbulten 134485 AB",
        "publiceringsdatum": "2024-02-28"
    },
    {
        "kungorelseid": "K150528/24",
        "uppgiftslamnare": "Bolagsverket",
        "kungorelsetyp": "Aktiebolagsregistret",
        "personOrgnummer": "",
        "namn": "Grundbulten 134491 AB",
        "publiceringsdatum": "2024-02-28"
    },
    {
        "kungorelseid": "K150535/24",
        "uppgiftslamnare": "Bolagsverket",
        "kungorelsetyp": "Aktiebolagsregistret",
        "personOrgnummer": "",
        "namn": "Grundbulten 134493 AB",
        "publiceringsdatum": "2024-02-28"
    }
]